unplugged/__init__.py
unplugged/admin.py
unplugged/apps.py
unplugged/baseplugin.py
unplugged/bootstrap.py
unplugged/commands.py
unplugged/jsonapi.py
unplugged/jsonschema.py
unplugged/pluginhandler.py
unplugged/routing.py
unplugged/scheduler.py
unplugged/schema.py
unplugged/signals.py
unplugged/urls.py
unplugged/utils.py
unplugged/fixtures/unplugged-initial.json
unplugged/libs/__init__.py
unplugged/libs/marshmallow_jsonschema/__init__.py
unplugged/libs/marshmallow_jsonschema/base.py
unplugged/libs/marshmallow_jsonschema/compat.py
unplugged/libs/marshmallow_jsonschema/validation.py
unplugged/migrations/0001_initial.py
unplugged/migrations/0002_simpleadminplugin_simpleadmintemplate.py
unplugged/migrations/0003_simpleadminplugin_display_name.py
unplugged/migrations/0004_auto_20190425_1302.py
unplugged/migrations/0005_auto_20190518_1557.py
unplugged/migrations/0006_auto_20190522_1907.py
unplugged/migrations/0007_auto_20190706_0817.py
unplugged/migrations/0008_auto_20190715_1944.py
unplugged/migrations/__init__.py
unplugged/models/__init__.py
unplugged/models/log.py
unplugged/models/plugin.py
unplugged/models/scheduler.py
unplugged/plugins/__init__.py
unplugged/plugins/service.py
unplugged/services/__init__.py
unplugged/services/admin/__init__.py
unplugged/services/admin/admin.py
unplugged/services/admin/apps.py
unplugged/services/admin/handler.py
unplugged/services/admin/models.py
unplugged/services/admin/migrations/0001_initial.py
unplugged/services/admin/migrations/0002_externalplugin.py
unplugged/services/admin/migrations/0003_auto_20200402_2029.py
unplugged/services/admin/migrations/0004_externalplugin_keywords.py
unplugged/services/admin/migrations/__init__.py
unplugged/services/admin/views/__init__.py
unplugged/services/admin/views/externalplugin.py
unplugged/services/admin/views/log.py
unplugged/services/admin/views/permission.py
unplugged/services/admin/views/plugin.py
unplugged/services/admin/views/scheduler.py
unplugged/services/admin/views/shared.py
unplugged-0.1.9.dist-info/LICENSE
unplugged-0.1.9.dist-info/METADATA
unplugged-0.1.9.dist-info/WHEEL
unplugged-0.1.9.dist-info/top_level.txt
unplugged-0.1.9.dist-info/RECORD
